{
    "title": "ドラゴン桜(モーニングコミックス)",
    "created": 1537623260,
    "updated": 1538319066,
    "lines": [
        "ドラゴン桜(モーニングコミックス)",
        "[https://images-fe.ssl-images-amazon.com/images/I/51FY7YZm-UL.jpg https://www.amazon.co.jp/dp/B009KWU5MM]",
        "",
        ">「教えてやる！東大は簡単だ！！」常識破り、処世術。弁護士・桜木による落ちこぼれ高校の再建計画、その内容は東大合格者100人！！　日本のルールは東大を出たやつが作っている。だから……東大に入れ！！　もっとも効率的な学習法を教えよう！！ https://amzn.to/2MUv1C7",
        "",
        "=====",
        "著者: [三田紀房]",
        "出版社: [講談社] (2003/10/23)",
        "ASIN: B009KWU5MM",
        "#漫画 #学園",
        ""
    ],
    "tags": [
        "漫画",
        "学園"
    ],
    "links": [
        "三田紀房",
        "講談社"
    ]
}