{
    "title": "バクマン。(ジャンプコミックスDIGITAL)",
    "created": 1537704963,
    "updated": 1538570615,
    "lines": [
        "バクマン。(ジャンプコミックスDIGITAL)",
        "[https://images-fe.ssl-images-amazon.com/images/I/510mjmUJzLL.jpg https://www.amazon.co.jp/dp/B00A47VW2Y]",
        "",
        ">一握りの者にしか得られない栄光を手にするため、険しい“マンガ道”を歩む決意をした二人。高い画力を持つ真城最高と、文才に長ける高木秋人がコンビを組み、新たなマンガ伝説を創る！　新時代成功物語開始!!",
        "",
        "　[マンガ]描きの漫画",
        " 本作で出てくる[マンガ]も面白そうでぜひ連載してほしいぐらい",
        "",
        "",
        "=====",
        "著者: [大場つぐみ] [小畑健]",
        "出版社: [集英社] (2009/1/5)",
        "ASIN: B00A47VW2Y",
        "#漫画",
        ""
    ],
    "tags": [
        "漫画"
    ],
    "links": [
        "マンガ",
        "大場つぐみ",
        "小畑健",
        "集英社"
    ]
}