{
    "title": "婚活は魔導書から(comico)",
    "created": 1538216241,
    "updated": 1538570738,
    "lines": [
        "婚活は魔導書から(comico)",
        "[https://images-fe.ssl-images-amazon.com/images/I/61s1vtW8gKL.jpg https://www.amazon.co.jp/dp/B079Y3PC6M]",
        "",
        "",
        "> [オカルト]好きでちょっぴり冷酷な結婚適齢期女子・サチ。ある日突然、[結婚]を宣言した彼女が、未来の旦那様として父に紹介したのは…[魔王]の息子・マモンだった!! ",
        "> だけど、人間と魔王子の結婚にはいくつもの障害が待ち受けていて――!?",
        "> 最凶娘が人間界と魔界をまたにかけ繰り広げる、ドタバタ嫁入りラブコメディ！",
        "",
        "",
        " [魔界]と人間界の異世界婚活",
        "",
        "",
        "=====",
        "著者: [ぽんとごたんだ]",
        "出版社: [comico] (2018/2/23)",
        "ASIN: B079Y3PC6M",
        "#漫画",
        ""
    ],
    "tags": [
        "漫画"
    ],
    "links": [
        "オカルト",
        "結婚",
        "魔王",
        "魔界",
        "ぽんとごたんだ",
        "comico"
    ]
}